slewpy/__init__.py
slewpy/hub.py
slewpy/priority.py
slewpy/schedule.py
slewpy/sensor.py
slewpy/serializer.py
slewpy/target.py
slewpy/transmission.py
slewpy/utils.py
slewpy-0.1.0.dist-info/METADATA
slewpy-0.1.0.dist-info/WHEEL
slewpy-0.1.0.dist-info/licenses/LICENSE
slewpy-0.1.0.dist-info/licenses/NOTICE
slewpy-0.1.0.dist-info/RECORD
