Metadata-Version: 2.4
Name: slewpy
Version: 0.1.0
Project-URL: Homepage, https://github.com/LLNL/slewpy/
Project-URL: Documentation, https://slewpy.readthedocs.io/en/latest/
Project-URL: Repository, https://github.com/LLNL/slewpy/
Project-URL: Issues, https://github.com/LLNL/slewpy/issues/
Project-URL: Changelog, https://github.com/LLNL/slewpy/releases/
Author: LLNL
License: MIT
License-File: LICENSE
License-File: NOTICE
Classifier: Intended Audience :: Science/Research
Classifier: License :: OSI Approved :: MIT License
Classifier: Operating System :: OS Independent
Classifier: Programming Language :: Python
Classifier: Programming Language :: Python :: 3
Requires-Python: >=3.8
Requires-Dist: astropy
Requires-Dist: llnl-ssapy
Requires-Dist: numpy
Requires-Dist: pandas
Requires-Dist: pyyaml
Requires-Dist: scipy
Requires-Dist: simpy
Requires-Dist: tqdm
